clasp/__init__.py
clasp/client.py
clasp/py.typed
clasp/types.py
clasp_to-3.3.1.dist-info/METADATA
clasp_to-3.3.1.dist-info/WHEEL
clasp_to-3.3.1.dist-info/RECORD
