Metadata-Version: 2.4
Name: clasp-to
Version: 3.3.1
Summary: CLASP client for Python - Creative Low-Latency Application Streaming Protocol
Project-URL: Homepage, https://clasp.to
Project-URL: Documentation, https://clasp.to/docs/python
Project-URL: Repository, https://github.com/lumencanvas/clasp
License: MIT
Keywords: artnet,clasp,creative,dmx,midi,osc,protocol
Classifier: Development Status :: 3 - Alpha
Classifier: Intended Audience :: Developers
Classifier: License :: OSI Approved :: MIT License
Classifier: Programming Language :: Python :: 3
Classifier: Programming Language :: Python :: 3.8
Classifier: Programming Language :: Python :: 3.9
Classifier: Programming Language :: Python :: 3.10
Classifier: Programming Language :: Python :: 3.11
Classifier: Programming Language :: Python :: 3.12
Classifier: Topic :: Multimedia
Classifier: Topic :: System :: Networking
Requires-Python: >=3.8
Requires-Dist: msgpack>=1.0.0
Requires-Dist: websockets>=10.0
Provides-Extra: dev
Requires-Dist: mypy>=1.0; extra == 'dev'
Requires-Dist: pytest-asyncio>=0.21; extra == 'dev'
Requires-Dist: pytest>=7.0; extra == 'dev'
